.coveragerc
.gitignore
.travis.yml
MANIFEST.in
Makefile
README.rst
requirements.txt
setup.py
tox.ini
l1ls/__init__.py
l1ls/l1_ls.py
l1ls/l1_ls_nonneg.py
l1ls/version.py
l1ls.egg-info/PKG-INFO
l1ls.egg-info/SOURCES.txt
l1ls.egg-info/dependency_links.txt
l1ls.egg-info/entry_points.txt
l1ls.egg-info/pbr.json
l1ls.egg-info/requires.txt
l1ls.egg-info/top_level.txt
l1ls.egg-info/zip-safe
tests/__init__.py
tests/base.py
tests/test_l1_ls.py
tests/test_version.py