Metadata-Version: 1.1
Name: l1ls
Version: 0.2.0
Summary: Python package for solving large scale L1 regularizedleast squares problems.
Home-page: https://github.com/musically-ut/l1-ls.py
Author: Utkarsh Upadhyay
Author-email: musically.ut@gmail.com
License: MIT
Keywords: L1 least-squares optimization
Platform: UNKNOWN
Classifier: Development Status :: 4 - Beta
Classifier: Intended Audience :: Developers
Classifier: License :: OSI Approved :: MIT License
Classifier: Natural Language :: English
Classifier: Programming Language :: Python :: 2.7
Classifier: Programming Language :: Python :: 3.4
Classifier: Operating System :: OS Independent
